container_source_policy/__init__.py
container_source_policy/__main__.py
container_source_policy/main.py
container_source_policy/bin/container-source-policy-linux-arm64/container-source-policy
container_source_policy-0.5.0.dist-info/METADATA
container_source_policy-0.5.0.dist-info/WHEEL
container_source_policy-0.5.0.dist-info/entry_points.txt
container_source_policy-0.5.0.dist-info/licenses/LICENSE
container_source_policy-0.5.0.dist-info/RECORD
