Metadata-Version: 2.4
Name: container-source-policy
Version: 0.5.0
Summary: Generate Buildx container source policy file for a given Dockerfile
Project-URL: Homepage, https://github.com/tinovyatkin/container-source-policy
Author-email: Konstantin Vyatkin <tino@vtkn.io>
License-Expression: MIT
License-File: LICENSE
Classifier: Operating System :: OS Independent
Classifier: Topic :: Software Development :: Version Control :: Git
Requires-Python: >=3.9
